git_plan/__cli__.py
git_plan/__init__.py
git_plan/cli/__init__.py
git_plan/cli/cli.py
git_plan/cli/commands/__init__.py
git_plan/cli/commands/add.py
git_plan/cli/commands/command.py
git_plan/cli/commands/commit.py
git_plan/cli/commands/delete.py
git_plan/cli/commands/edit.py
git_plan/cli/commands/init.py
git_plan/cli/commands/list.py
git_plan/conf.py
git_plan/constants.py
git_plan/containers.py
git_plan/exceptions.py
git_plan/model/__init__.py
git_plan/model/commit.py
git_plan/model/repository.py
git_plan/service/__init__.py
git_plan/service/git.py
git_plan/service/plan.py
git_plan/service/repository.py
git_plan/service/ui.py
git_plan/util/__init__.py
git_plan/util/decorators.py
git_plan/util/git.py
git_plan/util/unix.py
git_plan-0.2.4.dist-info/entry_points.txt
git_plan-0.2.4.dist-info/LICENSE
git_plan-0.2.4.dist-info/WHEEL
git_plan-0.2.4.dist-info/METADATA
git_plan-0.2.4.dist-info/RECORD
